szyfrowanie_json/__init__.py
szyfrowanie_json/main.py
szyfrowanie_json-0.1.0.dist-info/METADATA
szyfrowanie_json-0.1.0.dist-info/WHEEL
szyfrowanie_json-0.1.0.dist-info/top_level.txt
szyfrowanie_json-0.1.0.dist-info/RECORD
