Metadata-Version: 2.1
Name: szyfrowanie_json
Version: 0.1.0
Summary: Biblioteka do szyfrowania i odszyfrowywania plików JSON.
Home-page: https://github.com/Mateusz-Zareba/Szyforwanie_json
Author: Mateusz Zaręba
Author-email: zarebamateusz12@gmail.com
Classifier: Programming Language :: Python :: 3
Classifier: License :: OSI Approved :: MIT License
Classifier: Operating System :: OS Independent
Requires-Python: >=3.6
Requires-Dist: cryptography
